pydantic_config/__init__.py
pydantic_config/main.py
pydantic_config/merge.py
pydantic_config/readers.py
pydantic_config-0.3.0.dist-info/LICENSE
pydantic_config-0.3.0.dist-info/METADATA
pydantic_config-0.3.0.dist-info/WHEEL
pydantic_config-0.3.0.dist-info/top_level.txt
pydantic_config-0.3.0.dist-info/RECORD
