Metadata-Version: 2.1
Name: pydantic-config
Version: 0.3.0
Summary: Support for Pydantic settings configuration file loading
Author: Jordan Shaw
Project-URL: Homepage, https://github.com/jordantshaw/pydantic-config
Classifier: Natural Language :: English
Classifier: Intended Audience :: Developers
Classifier: Development Status :: 4 - Beta
Classifier: Programming Language :: Python :: 3
Classifier: License :: OSI Approved :: MIT License
Classifier: Operating System :: OS Independent
Requires-Python: >=3.7
License-File: LICENSE
Requires-Dist: pydantic-settings>=2.0.1
Provides-Extra: yaml
Requires-Dist: pyyaml>=5.1; extra == "yaml"
Provides-Extra: toml
Requires-Dist: tomli>=2.0.0; extra == "toml"
Provides-Extra: all
Requires-Dist: pyyaml>=5.1; extra == "all"
Requires-Dist: tomli>=2.0.0; extra == "all"
Provides-Extra: dev
Requires-Dist: pytest; extra == "dev"
Requires-Dist: twine; extra == "dev"
Requires-Dist: build; extra == "dev"
Requires-Dist: pyyaml>=5.1; extra == "dev"
Requires-Dist: python-dotenv>=0.15.0; extra == "dev"
Requires-Dist: tomli>=2.0.0; extra == "dev"
Provides-Extra: test
Requires-Dist: pytest; extra == "test"
Requires-Dist: pyyaml==5.1; extra == "test"
Requires-Dist: python-dotenv>=0.15.0; extra == "test"
Requires-Dist: tomli>=2.0.0; extra == "test"
